testfixtures/__init__.py
testfixtures/comparison.py
testfixtures/compat.py
testfixtures/datetime.py
testfixtures/django.py
testfixtures/logcapture.py
testfixtures/mock.py
testfixtures/outputcapture.py
testfixtures/popen.py
testfixtures/py.typed
testfixtures/replace.py
testfixtures/resolve.py
testfixtures/rmtree.py
testfixtures/shouldraise.py
testfixtures/shouldwarn.py
testfixtures/sybil.py
testfixtures/tempdirectory.py
testfixtures/twisted.py
testfixtures/utils.py
testfixtures/version.txt
testfixtures/tests/__init__.py
testfixtures/tests/sample1.py
testfixtures/tests/sample2.py
testfixtures/tests/sample3.py
testfixtures/tests/test_compare.py
testfixtures/tests/test_compare_typed.py
testfixtures/tests/test_comparison.py
testfixtures/tests/test_date.py
testfixtures/tests/test_datetime.py
testfixtures/tests/test_diff.py
testfixtures/tests/test_generator.py
testfixtures/tests/test_log_capture.py
testfixtures/tests/test_logcapture.py
testfixtures/tests/test_mappingcomparison.py
testfixtures/tests/test_mock.py
testfixtures/tests/test_outputcapture.py
testfixtures/tests/test_popen.py
testfixtures/tests/test_popen_docs.py
testfixtures/tests/test_rangecomparison.py
testfixtures/tests/test_replace.py
testfixtures/tests/test_replacer.py
testfixtures/tests/test_roundcomparison.py
testfixtures/tests/test_sequencecomparison.py
testfixtures/tests/test_should_raise.py
testfixtures/tests/test_shouldwarn.py
testfixtures/tests/test_stringcomparison.py
testfixtures/tests/test_sybil.py
testfixtures/tests/test_tempdir.py
testfixtures/tests/test_tempdirectory.py
testfixtures/tests/test_time.py
testfixtures/tests/test_twisted.py
testfixtures/tests/test_wrap.py
testfixtures/tests/test_django/__init__.py
testfixtures/tests/test_django/manage.py
testfixtures/tests/test_django/models.py
testfixtures/tests/test_django/settings.py
testfixtures/tests/test_django/test_compare.py
testfixtures/tests/test_django/test_shouldraise.py
testfixtures-9.2.0.dist-info/licenses/LICENSE.txt
testfixtures-9.2.0.dist-info/METADATA
testfixtures-9.2.0.dist-info/WHEEL
testfixtures-9.2.0.dist-info/top_level.txt
testfixtures-9.2.0.dist-info/RECORD
